gcrack/__init__.py
gcrack/boundary_conditions.py
gcrack/domain.py
gcrack/exporters.py
gcrack/fcrack.py
gcrack/gcrack.py
gcrack/icrack.py
gcrack/lefm.py
gcrack/models.py
gcrack/optimization_solvers.py
gcrack/postprocess.py
gcrack/sif.py
gcrack/solvers.py
gcrack/utils/__init__.py
gcrack/utils/expression_parsers.py
gcrack/utils/geometry.py
gcrack/utils/williams_series.py
gcrack-2026.1.26.dist-info/licenses/LICENSE
gcrack-2026.1.26.dist-info/METADATA
gcrack-2026.1.26.dist-info/WHEEL
gcrack-2026.1.26.dist-info/top_level.txt
gcrack-2026.1.26.dist-info/RECORD
