Metadata-Version: 2.4
Name: gcrack
Version: 2026.1.26
Summary: Solver for Linear Elastic Fracture Mechanics problems 
Author-email: Flavien Loiseau <flavien.loiseau@ensta.fr>
License:                                  Apache License
Requires-Python: >=3.10.0
License-File: LICENSE
Dynamic: license-file
